mf_smem/VERSION
mf_smem/__init__.py
mf_smem/_pymf_smem.cpython-311-aarch64-linux-gnu.so
mf_smem.libs/libmf_hybm_core-4a4dca26.so
mf_smem.libs/libmf_smem-0b161aff.so
mf_smem-1.0.0.dist-info/METADATA
mf_smem-1.0.0.dist-info/WHEEL
mf_smem-1.0.0.dist-info/top_level.txt
mf_smem-1.0.0.dist-info/RECORD
