Metadata-Version: 2.4
Name: mf_smem
Version: 1.0.0
Summary: python api for smem
Home-page: https://gitee.com/ascend/memfabric_hybrid
Author: 
Author-email: 
License: Apache License Version 2.0
Requires-Python: >=3.7
Dynamic: home-page
Dynamic: license
Dynamic: requires-python
Dynamic: summary
